french_typo/__init__.py
french_typo/formatter.py
french_typo/rules/__init__.py
french_typo/rules/numbers.py
french_typo/rules/spaces.py
french_typo/rules/units.py
french_typo-0.2.1.dist-info/licenses/LICENSE
french_typo-0.2.1.dist-info/METADATA
french_typo-0.2.1.dist-info/WHEEL
french_typo-0.2.1.dist-info/top_level.txt
french_typo-0.2.1.dist-info/RECORD
