Metadata-Version: 2.4
Name: french-typo
Version: 0.2.1
Summary: Moteur agnostique de correction typographique française
License: MIT
Requires-Python: >=3.8
License-File: LICENSE
Dynamic: license-file
